{"NABkP9i4t4mIGSpFn73WIA==":"background1.jpg","QrU8O1Opr88bO9V4MNw7Yg==":"%ED%85%8C%EC%8A%A4%ED%8A%B8%20%EC%9D%B4%EB%AF%B8%EC%A7%80-960x720.png","UoyLAp2yUu4cglRLnk2ztQ==":"product-491x343.png","sowR02PQioYEiutZXMOM9Q==":"mbr-1920x1357.jpg","lQNPGBswOJkLIx3dKI2eQw==":"%ED%85%8C%EC%8A%A4%ED%8A%B8%20%EC%9D%B4%EB%AF%B8%EC%A7%80-960x720.png","M61mMFNX57u3e1TfIjKr3w==":"mbr-1332x834.jpg","/5TxP6rB5Xsj6wML99MSww==":"logo2.png","NpTez4WahHv9CI9mZfgrrg==":"kob%20logo-122x64.jpg","Os1hpkyKHdJTZJYYSjSiXg==":"01.jpg","Q8kyWdiPLYJ/4F1Ss+9IyA==":"03.jpg","D/MJwuutwIhlmcioKCvGqA==":"04.jpg","HoeEF4HfT9nMa9Cg+v0y1w==":"02.jpg","0OOE1Usrtktm437Z/qTMRQ==":"background2.jpg","co8jr7G875ZW8O+GPwrosg==":"ceo-492x724.jpg","z/0YCnmoAf/ilduWHg4hgg==":"%ED%9A%8C%EC%82%AC%EC%86%8C%EA%B0%9C%EC%84%9C%20%ED%91%9C%EC%A7%80-1752x1001.jpg","/dgVxnc/U0V2q6aSolgK4A==":"_mg-8678-2000x1537.png","eFJcjqU6CZFhd5937KLWag==":"20190108162033-1-1654x2340.jpg","D9GiB0RZpGZk1gS/eSAA/w==":"20190108162022-1-1654x2340.jpg","H3tZpc06RmbLR1iSrRr8IQ==":"20190108162010-1-1654x2340.jpg","+CQNSI0aHmnhehd9vWJGMA==":"20190108162000-1-1654x2340.jpg","PcZ2+BS9CVEbwVnaGwBfig==":"_mg-8646-1144x1312.png","wQJERNt83+Bqhf5Q8pyFtw==":"_mg-8648-1280x1400.png","s6Ag6Gw4leRo18gIqxF8wQ==":"_mg-8672-848x536.png","QxidAUuQ19LKZYbyMYNYJQ==":"_mg-8652-1600x1344.png","2rWfhNWJYRL+Xjtl9GYNaA==":"_mg-8670-1280x752.png","PvMIDb4tpDkatf1i5PwpLg==":"_mg-8651-1368x1440.png","ce8Q0fdgfdIhbTBMPzOhTw==":"_mg-8655-1576x1888.png","E6Uwf6cdgPuHTTLqZg3F9g==":"20190108161942-1-2000x1414.jpg","sycA9yxzWSwhZPGUzMO3DA==":"all-514x562.png","0MxUqiOLASi3ZyJZXU1WKQ==":"cfb-512x563.png","FHk9Jc45CRlKCVAMjWQLEg==":"csb-514x563.png","VULIFQ8eHykXb76uBI+nxg==":"obp-514x563.png","tqonXlUW4HH6ofpHFKQnsA==":"obr-514x563.png","sMzdqY8CvEX3OWZEhwaVkw==":"ofb-515x565.png","oWuz9e1WzoUuE5/5ac3MIg==":"osb-514x562.png","0TThxMI4UMF8SG9pkg65NA==":"obw-514x536.png","iPS+k/WZDjrtb5oh0Xu2pQ==":"mtech_japan_logo-200x200.jpg","93hRTAJcy5lmZiCmWvxU1A==":"%EB%8B%A4%EC%9A%B4%EB%A1%9C%EB%93%9C-225x225.jpg"}